{
  "https://fiscal.ai/company/NasdaqGS-MCHP/": {
    "Rev 3Yr": "-18%",
    "Rev 5Yr": "-4.2%",
    "Rev 10Yr": "7%",
    "Dil EPS 3Yr": "-48.3%",
    "Dil EPS 5Yr": "-17.3%",
    "Dil EPS 10Yr": "-6.3%",
    "Rev Fwd 2Yr": "11.3%",
    "EBITDA Fwd 2Yr": "25.7%",
    "EPS Fwd 2Yr": "—",
    "EPS LT Growth Est": "32.4%"
  },
  "https://finance.yahoo.com/quote/MCHP/key-statistics?p=MCHP": {
    "__type__": "bs4_tag",
    "html": "<section class=\"yf-18eg72q\" data-testid=\"qsp-statistics\">\n <header class=\"medium mb-4 yf-1kayatz font-condensed\">\n  <h3 class=\"header yf-1kayatz\">\n   Valuation Measures\n  </h3>\n </header>\n <div class=\"table-container yf-18eg72q\">\n  <table class=\"table yf-18eg72q\">\n   <thead>\n    <tr class=\"yf-18eg72q\">\n     <th class=\"yf-18eg72q\">\n     </th>\n     <th class=\"yf-18eg72q\">\n      Current\n     </th>\n     <th class=\"yf-18eg72q\">\n      9/30/2025\n     </th>\n     <th class=\"yf-18eg72q\">\n      6/30/2025\n     </th>\n     <th class=\"yf-18eg72q\">\n      3/31/2025\n     </th>\n     <th class=\"yf-18eg72q\">\n      12/31/2024\n     </th>\n     <th class=\"yf-18eg72q\">\n      9/30/2024\n     </th>\n    </tr>\n   </thead>\n   <tbody>\n    <tr class=\"yf-18eg72q alt\">\n     <td class=\"yf-18eg72q\">\n      Market Cap\n     </td>\n     <td class=\"yf-18eg72q\">\n      40.03B\n     </td>\n     <td class=\"yf-18eg72q\">\n      34.71B\n     </td>\n     <td class=\"yf-18eg72q\">\n      37.98B\n     </td>\n     <td class=\"yf-18eg72q\">\n      26.08B\n     </td>\n     <td class=\"yf-18eg72q\">\n      30.84B\n     </td>\n     <td class=\"yf-18eg72q\">\n      43.12B\n     </td>\n    </tr>\n    <tr class=\"yf-18eg72q\">\n     <td class=\"yf-18eg72q\">\n      Enterprise Value\n     </td>\n     <td class=\"yf-18eg72q\">\n      45.21B\n     </td>\n     <td class=\"yf-18eg72q\">\n      39.64B\n     </td>\n     <td class=\"yf-18eg72q\">\n      42.87B\n     </td>\n     <td class=\"yf-18eg72q\">\n      32.28B\n     </td>\n     <td class=\"yf-18eg72q\">\n      37.01B\n     </td>\n     <td class=\"yf-18eg72q\">\n      49.00B\n     </td>\n    </tr>\n    <tr class=\"yf-18eg72q alt\">\n     <td class=\"yf-18eg72q\">\n      Trailing P/E\n     </td>\n     <td class=\"yf-18eg72q\">\n      31.39\n     </td>\n     <td class=\"yf-18eg72q\">\n      --\n     </td>\n     <td class=\"yf-18eg72q\">\n      --\n     </td>\n     <td class=\"yf-18eg72q\">\n      84.93\n     </td>\n     <td class=\"yf-18eg72q\">\n      39.83\n     </td>\n     <td class=\"yf-18eg72q\">\n      31.99\n     </td>\n    </tr>\n    <tr class=\"yf-18eg72q\">\n     <td class=\"yf-18eg72q\">\n      Forward P/E\n     </td>\n     <td class=\"yf-18eg72q\">\n      29.59\n     </td>\n     <td class=\"yf-18eg72q\">\n      40.98\n     </td>\n     <td class=\"yf-18eg72q\">\n      49.51\n     </td>\n     <td class=\"yf-18eg72q\">\n      33.00\n     </td>\n     <td class=\"yf-18eg72q\">\n      19.92\n     </td>\n     <td class=\"yf-18eg72q\">\n      40.00\n     </td>\n    </tr>\n    <tr class=\"yf-18eg72q alt\">\n     <td class=\"yf-18eg72q\">\n      PEG Ratio (5yr expected)\n     </td>\n     <td class=\"yf-18eg72q\">\n      5.70\n     </td>\n     <td class=\"yf-18eg72q\">\n      --\n     </td>\n     <td class=\"yf-18eg72q\">\n      --\n     </td>\n     <td class=\"yf-18eg72q\">\n      --\n     </td>\n     <td class=\"yf-18eg72q\">\n      7.09\n     </td>\n     <td class=\"yf-18eg72q\">\n      5.80\n     </td>\n    </tr>\n    <tr class=\"yf-18eg72q\">\n     <td class=\"yf-18eg72q\">\n      Price/Sales\n     </td>\n     <td class=\"yf-18eg72q\">\n      9.47\n     </td>\n     <td class=\"yf-18eg72q\">\n      8.16\n     </td>\n     <td class=\"yf-18eg72q\">\n      8.59\n     </td>\n     <td class=\"yf-18eg72q\">\n      5.52\n     </td>\n     <td class=\"yf-18eg72q\">\n      5.68\n     </td>\n     <td class=\"yf-18eg72q\">\n      6.65\n     </td>\n    </tr>\n    <tr class=\"yf-18eg72q alt\">\n     <td class=\"yf-18eg72q\">\n      Price/Book\n     </td>\n     <td class=\"yf-18eg72q\">\n      5.98\n     </td>\n     <td class=\"yf-18eg72q\">\n      5.06\n     </td>\n     <td class=\"yf-18eg72q\">\n      5.37\n     </td>\n     <td class=\"yf-18eg72q\">\n      4.32\n     </td>\n     <td class=\"yf-18eg72q\">\n      4.91\n     </td>\n     <td class=\"yf-18eg72q\">\n      6.73\n     </td>\n    </tr>\n    <tr class=\"yf-18eg72q\">\n     <td class=\"yf-18eg72q\">\n      Enterprise Value/Revenue\n     </td>\n     <td class=\"yf-18eg72q\">\n      10.73\n     </td>\n     <td class=\"yf-18eg72q\">\n      9.36\n     </td>\n     <td class=\"yf-18eg72q\">\n      9.74\n     </td>\n     <td class=\"yf-18eg72q\">\n      6.79\n     </td>\n     <td class=\"yf-18eg72q\">\n      6.73\n     </td>\n     <td class=\"yf-18eg72q\">\n      7.44\n     </td>\n    </tr>\n    <tr class=\"yf-18eg72q alt\">\n     <td class=\"yf-18eg72q\">\n      Enterprise Value/EBITDA\n     </td>\n     <td class=\"yf-18eg72q\">\n      59.09\n     </td>\n     <td class=\"yf-18eg72q\">\n      47.11\n     </td>\n     <td class=\"yf-18eg72q\">\n      41.21\n     </td>\n     <td class=\"yf-18eg72q\">\n      22.65\n     </td>\n     <td class=\"yf-18eg72q\">\n      18.80\n     </td>\n     <td class=\"yf-18eg72q\">\n      17.95\n     </td>\n    </tr>\n   </tbody>\n  </table>\n </div>\n</section>\n"
  }
}