{
  "https://fiscal.ai/company/HOSE-PDR/": {
    "Rev 3Yr": "-16%",
    "Rev 5Yr": "-14.5%",
    "Rev 10Yr": "9.2%",
    "Dil EPS 3Yr": "-57.6%",
    "Dil EPS 5Yr": "-33.1%",
    "Dil EPS 10Yr": "3%",
    "Rev Fwd 2Yr": "33.3%",
    "EBITDA Fwd 2Yr": "48.6%",
    "EPS Fwd 2Yr": "56.4%",
    "EPS LT Growth Est": "46%"
  },
  "https://finance.yahoo.com/quote/PDR.VN/key-statistics?p=PDR.VN": {
    "__type__": "bs4_tag",
    "html": "<section class=\"yf-18eg72q\" data-testid=\"qsp-statistics\">\n <header class=\"medium mb-4 yf-1kayatz font-condensed\">\n  <h3 class=\"header yf-1kayatz\">\n   Valuation Measures\n  </h3>\n </header>\n <div class=\"table-container yf-18eg72q\">\n  <table class=\"table yf-18eg72q\">\n   <thead>\n    <tr class=\"yf-18eg72q\">\n     <th class=\"yf-18eg72q\">\n     </th>\n     <th class=\"yf-18eg72q\">\n      Current\n     </th>\n     <th class=\"yf-18eg72q\">\n      6/30/2025\n     </th>\n     <th class=\"yf-18eg72q\">\n      3/31/2025\n     </th>\n     <th class=\"yf-18eg72q\">\n      12/31/2024\n     </th>\n     <th class=\"yf-18eg72q\">\n      9/30/2024\n     </th>\n     <th class=\"yf-18eg72q\">\n      6/30/2024\n     </th>\n    </tr>\n   </thead>\n   <tbody>\n    <tr class=\"yf-18eg72q alt\">\n     <td class=\"yf-18eg72q\">\n      Market Cap\n     </td>\n     <td class=\"yf-18eg72q\">\n      17.15T\n     </td>\n     <td class=\"yf-18eg72q\">\n      15.76T\n     </td>\n     <td class=\"yf-18eg72q\">\n      16.90T\n     </td>\n     <td class=\"yf-18eg72q\">\n      18.07T\n     </td>\n     <td class=\"yf-18eg72q\">\n      19.65T\n     </td>\n     <td class=\"yf-18eg72q\">\n      19.38T\n     </td>\n    </tr>\n    <tr class=\"yf-18eg72q\">\n     <td class=\"yf-18eg72q\">\n      Enterprise Value\n     </td>\n     <td class=\"yf-18eg72q\">\n      22.92T\n     </td>\n     <td class=\"yf-18eg72q\">\n      20.91T\n     </td>\n     <td class=\"yf-18eg72q\">\n      21.78T\n     </td>\n     <td class=\"yf-18eg72q\">\n      22.25T\n     </td>\n     <td class=\"yf-18eg72q\">\n      22.62T\n     </td>\n     <td class=\"yf-18eg72q\">\n      22.89T\n     </td>\n    </tr>\n    <tr class=\"yf-18eg72q alt\">\n     <td class=\"yf-18eg72q\">\n      Trailing P/E\n     </td>\n     <td class=\"yf-18eg72q\">\n      85.21\n     </td>\n     <td class=\"yf-18eg72q\">\n      105.56\n     </td>\n     <td class=\"yf-18eg72q\">\n      38.08\n     </td>\n     <td class=\"yf-18eg72q\">\n      40.73\n     </td>\n     <td class=\"yf-18eg72q\">\n      37.93\n     </td>\n     <td class=\"yf-18eg72q\">\n      25.30\n     </td>\n    </tr>\n    <tr class=\"yf-18eg72q\">\n     <td class=\"yf-18eg72q\">\n      Forward P/E\n     </td>\n     <td class=\"yf-18eg72q\">\n      18.90\n     </td>\n     <td class=\"yf-18eg72q\">\n      34.36\n     </td>\n     <td class=\"yf-18eg72q\">\n      30.49\n     </td>\n     <td class=\"yf-18eg72q\">\n      28.25\n     </td>\n     <td class=\"yf-18eg72q\">\n      23.70\n     </td>\n     <td class=\"yf-18eg72q\">\n      31.35\n     </td>\n    </tr>\n    <tr class=\"yf-18eg72q alt\">\n     <td class=\"yf-18eg72q\">\n      PEG Ratio (5yr expected)\n     </td>\n     <td class=\"yf-18eg72q\">\n      --\n     </td>\n     <td class=\"yf-18eg72q\">\n      --\n     </td>\n     <td class=\"yf-18eg72q\">\n      --\n     </td>\n     <td class=\"yf-18eg72q\">\n      --\n     </td>\n     <td class=\"yf-18eg72q\">\n      --\n     </td>\n     <td class=\"yf-18eg72q\">\n      --\n     </td>\n    </tr>\n    <tr class=\"yf-18eg72q\">\n     <td class=\"yf-18eg72q\">\n      Price/Sales\n     </td>\n     <td class=\"yf-18eg72q\">\n      10.63\n     </td>\n     <td class=\"yf-18eg72q\">\n      14.36\n     </td>\n     <td class=\"yf-18eg72q\">\n      70.09\n     </td>\n     <td class=\"yf-18eg72q\">\n      74.98\n     </td>\n     <td class=\"yf-18eg72q\">\n      33.12\n     </td>\n     <td class=\"yf-18eg72q\">\n      32.99\n     </td>\n    </tr>\n    <tr class=\"yf-18eg72q alt\">\n     <td class=\"yf-18eg72q\">\n      Price/Book\n     </td>\n     <td class=\"yf-18eg72q\">\n      1.44\n     </td>\n     <td class=\"yf-18eg72q\">\n      1.48\n     </td>\n     <td class=\"yf-18eg72q\">\n      1.54\n     </td>\n     <td class=\"yf-18eg72q\">\n      1.64\n     </td>\n     <td class=\"yf-18eg72q\">\n      1.79\n     </td>\n     <td class=\"yf-18eg72q\">\n      2.16\n     </td>\n    </tr>\n    <tr class=\"yf-18eg72q\">\n     <td class=\"yf-18eg72q\">\n      Enterprise Value/Revenue\n     </td>\n     <td class=\"yf-18eg72q\">\n      14.21\n     </td>\n     <td class=\"yf-18eg72q\">\n      19.06\n     </td>\n     <td class=\"yf-18eg72q\">\n      90.35\n     </td>\n     <td class=\"yf-18eg72q\">\n      92.32\n     </td>\n     <td class=\"yf-18eg72q\">\n      38.14\n     </td>\n     <td class=\"yf-18eg72q\">\n      38.96\n     </td>\n    </tr>\n    <tr class=\"yf-18eg72q alt\">\n     <td class=\"yf-18eg72q\">\n      Enterprise Value/EBITDA\n     </td>\n     <td class=\"yf-18eg72q\">\n      36.77\n     </td>\n     <td class=\"yf-18eg72q\">\n      35.67\n     </td>\n     <td class=\"yf-18eg72q\">\n      23.86\n     </td>\n     <td class=\"yf-18eg72q\">\n      24.38\n     </td>\n     <td class=\"yf-18eg72q\">\n      22.93\n     </td>\n     <td class=\"yf-18eg72q\">\n      17.82\n     </td>\n    </tr>\n   </tbody>\n  </table>\n </div>\n</section>\n"
  }
}