{
  "ticker": "TSN",
  "crprice": 60.36000061035156,
  "mck_info": {
    "address1": "2200 West Don Tyson Parkway",
    "city": "Springdale",
    "state": "AR",
    "zip": "72762-6999",
    "country": "United States",
    "phone": "(479) 290-4000",
    "website": "https://www.tysonfoods.com",
    "industry": "Farm Products",
    "industryKey": "farm-products",
    "industryDisp": "Farm Products",
    "sector": "Consumer Defensive",
    "sectorKey": "consumer-defensive",
    "sectorDisp": "Consumer Defensive",
    "longBusinessSummary": "Tyson Foods, Inc., together with its subsidiaries, operates as a food company worldwide. It operates through four segments: Beef, Pork, Chicken, and Prepared Foods. The company processes live fed cattle and hogs; fabricates dressed beef and pork carcasses into primal and sub-primal meat cuts, as well as case ready beef and pork, and fully cooked meats; raises and processes chickens into fresh, frozen, and value-added chicken products, including breaded chicken strips, nuggets, patties, and other ready-to-fix or fully cooked chicken parts; and supplies poultry breeding stock. It also manufactures and markets frozen and refrigerated food products, including ready-to-eat sandwiches, flame-grilled hamburgers, Philly steaks, pepperoni, bacon, breakfast sausage, turkey, lunchmeat, hot dogs, flour and corn tortilla products, appetizers, snacks, prepared meals, ethnic foods, side dishes, meat dishes, breadsticks, and processed meats under the Tyson, Jimmy Dean, Hillshire Farm, Ball Park, Wright, Aidells, Gallo Salame, ibp, and State Fair brands. The company sells its products through its sales staff to grocery retailers, grocery wholesalers, meat distributors, warehouse club stores, military commissaries, industrial food processing companies, chain restaurants or their distributors, live markets, international export companies, and domestic distributors who serve restaurants and food service operations, such as plant and school cafeterias, convenience stores, hospitals, and other vendors, as well as through independent brokers and trading companies. Tyson Foods, Inc. was founded in 1935 and is headquartered in Springdale, Arkansas.",
    "fullTimeEmployees": 133000,
    "companyOfficers": [
      {
        "maxAge": 1,
        "name": "Mr. Donnie D. King",
        "age": 63,
        "title": "President, CEO & Director",
        "yearBorn": 1962,
        "fiscalYear": 2025,
        "totalPay": 11841180,
        "exercisedValue": 0,
        "unexercisedValue": 449843
      },
      {
        "maxAge": 1,
        "name": "Mr. Curt T. Calaway",
        "age": 51,
        "title": "Chief Financial Officer",
        "yearBorn": 1974,
        "fiscalYear": 2025,
        "totalPay": 2774974,
        "exercisedValue": 0,
        "unexercisedValue": 40389
      },
      {
        "maxAge": 1,
        "name": "Mr. Devin  Cole",
        "age": 55,
        "title": "Chief Operating Officer",
        "yearBorn": 1970,
        "fiscalYear": 2025,
        "totalPay": 4041977,
        "exercisedValue": 0,
        "unexercisedValue": 0
      },
      {
        "maxAge": 1,
        "name": "Mr. Adam  Deckinger",
        "age": 49,
        "title": "Chief Legal & Administrative Officer",
        "yearBorn": 1976,
        "fiscalYear": 2025,
        "totalPay": 3032561,
        "exercisedValue": 0,
        "unexercisedValue": 51124
      },
      {
        "maxAge": 1,
        "name": "Mr. Wes  Morris",
        "age": 59,
        "title": "Executive Officer",
        "yearBorn": 1966,
        "fiscalYear": 2025,
        "totalPay": 3084529,
        "exercisedValue": 352257,
        "unexercisedValue": 0
      },
      {
        "maxAge": 1,
        "name": "Ms. Lori J. Bondar",
        "age": 64,
        "title": "Senior Vice President of Finance & Accounting",
        "yearBorn": 1961,
        "fiscalYear": 2025,
        "exercisedValue": 0,
        "unexercisedValue": 0
      },
      {
        "maxAge": 1,
        "name": "Mr. Mike  Wheeler",
        "title": "Chief Technology Officer",
        "fiscalYear": 2025,
        "exercisedValue": 0,
        "unexercisedValue": 0
      },
      {
        "maxAge": 1,
        "name": "Jon  Kathol",
        "title": "Vice President of Investor Relations",
        "fiscalYear": 2025,
        "exercisedValue": 0,
        "unexercisedValue": 0
      },
      {
        "maxAge": 1,
        "name": "Ms. Jacqueline  Hanson",
        "age": 56,
        "title": "Chief People Officer",
        "yearBorn": 1969,
        "fiscalYear": 2025,
        "exercisedValue": 0,
        "unexercisedValue": 0
      },
      {
        "maxAge": 1,
        "name": "Mr. Jerry  Holbrook",
        "title": "Senior Vice President of Sales & Marketing of Tyson Fresh Meats",
        "fiscalYear": 2025,
        "exercisedValue": 0,
        "unexercisedValue": 0
      }
    ],
    "auditRisk": 10,
    "boardRisk": 10,
    "compensationRisk": 9,
    "shareHolderRightsRisk": 10,
    "overallRisk": 10,
    "governanceEpochDate": 1768176000,
    "compensationAsOfEpochDate": 1767139200,
    "irWebsite": "http://ir.tyson.com/phoenix.zhtml?c=65476&p=irol-irHome",
    "executiveTeam": [],
    "maxAge": 86400,
    "priceHint": 2,
    "previousClose": 60.08,
    "open": 60.18,
    "dayLow": 60.1,
    "dayHigh": 60.715,
    "regularMarketPreviousClose": 60.08,
    "regularMarketOpen": 60.18,
    "regularMarketDayLow": 60.1,
    "regularMarketDayHigh": 60.715,
    "dividendRate": 2.04,
    "dividendYield": 3.4,
    "exDividendDate": 1772150400,
    "payoutRatio": 1.5038,
    "fiveYearAvgDividendYield": 2.99,
    "beta": 0.467,
    "trailingPE": 45.383457,
    "forwardPE": 13.790803,
    "volume": 485470,
    "regularMarketVolume": 485470,
    "averageVolume": 2998177,
    "averageVolume10days": 2713520,
    "averageDailyVolume10Day": 2713520,
    "bid": 60.41,
    "ask": 60.45,
    "bidSize": 600,
    "askSize": 100,
    "marketCap": 21310513152,
    "fiftyTwoWeekLow": 50.56,
    "fiftyTwoWeekHigh": 64.36,
    "allTimeHigh": 100.72,
    "allTimeLow": 1.611111,
    "priceToSalesTrailing12Months": 0.39144236,
    "fiftyDayAverage": 56.3932,
    "twoHundredDayAverage": 56.0038,
    "trailingAnnualDividendRate": 2.0,
    "trailingAnnualDividendYield": 0.03328895,
    "currency": "USD",
    "tradeable": false,
    "enterpriseValue": 29819490304,
    "profitMargins": 0.00871,
    "floatShares": 275834099,
    "sharesOutstanding": 283047857,
    "sharesShort": 8870425,
    "sharesShortPriorMonth": 10670064,
    "sharesShortPreviousMonthDate": 1764288000,
    "dateShortInterest": 1767139200,
    "sharesPercentSharesOut": 0.0251,
    "heldPercentInsiders": 0.01638,
    "heldPercentInstitutions": 0.90204,
    "shortRatio": 3.1,
    "shortPercentOfFloat": 0.032,
    "impliedSharesOutstanding": 353056862,
    "bookValue": 51.232,
    "priceToBook": 1.17817,
    "lastFiscalYearEnd": 1758931200,
    "nextFiscalYearEnd": 1790467200,
    "mostRecentQuarter": 1758931200,
    "earningsQuarterlyGrowth": -0.868,
    "netIncomeToCommon": 474000000,
    "trailingEps": 1.33,
    "forwardEps": 4.37683,
    "lastSplitFactor": "3:2",
    "lastSplitDate": 856224000,
    "enterpriseToRevenue": 0.548,
    "enterpriseToEbitda": 10.544,
    "52WeekChange": 0.07747495,
    "SandP52WeekChange": 0.17039418,
    "lastDividendValue": 0.51,
    "lastDividendDate": 1764547200,
    "quoteType": "EQUITY",
    "currentPrice": 60.36,
    "targetHighPrice": 80.0,
    "targetLowPrice": 55.0,
    "targetMeanPrice": 64.75,
    "targetMedianPrice": 63.5,
    "recommendationMean": 2.35714,
    "recommendationKey": "buy",
    "numberOfAnalystOpinions": 12,
    "totalCash": 1228999936,
    "totalCashPerShare": 3.481,
    "ebitda": 2828000000,
    "totalDebt": 9694999552,
    "quickRatio": 0.587,
    "currentRatio": 1.552,
    "totalRevenue": 54441000960,
    "debtToEquity": 53.19,
    "revenuePerShare": 152.496,
    "returnOnAssets": 0.025710002,
    "returnOnEquity": 0.0276,
    "grossProfits": 3644000000,
    "freeCashflow": 1187500032,
    "operatingCashflow": 2155000064,
    "earningsGrowth": -0.87,
    "revenueGrowth": 0.022,
    "grossMargins": 0.066929996,
    "ebitdaMargins": 0.05195,
    "operatingMargins": -0.0049799997,
    "financialCurrency": "USD",
    "symbol": "TSN",
    "language": "en-US",
    "region": "US",
    "typeDisp": "Equity",
    "quoteSourceName": "Nasdaq Real Time Price",
    "triggerable": true,
    "customPriceAlertConfidence": "HIGH",
    "priceEpsCurrentYear": 15.639818,
    "fiftyDayAverageChange": 3.9668007,
    "fiftyDayAverageChangePercent": 0.070341825,
    "twoHundredDayAverageChange": 4.356201,
    "twoHundredDayAverageChangePercent": 0.07778403,
    "sourceInterval": 15,
    "exchangeDataDelayedBy": 0,
    "averageAnalystRating": "2.4 - Buy",
    "marketState": "REGULAR",
    "hasPrePostMarketData": true,
    "firstTradeDateMilliseconds": 322151400000,
    "regularMarketChange": 0.27999878,
    "regularMarketDayRange": "60.1 - 60.715",
    "fullExchangeName": "NYSE",
    "averageDailyVolume3Month": 2998177,
    "fiftyTwoWeekLowChange": 9.799999,
    "fiftyTwoWeekLowChangePercent": 0.19382909,
    "fiftyTwoWeekRange": "50.56 - 64.36",
    "fiftyTwoWeekHighChange": -4.0,
    "fiftyTwoWeekHighChangePercent": -0.062150404,
    "fiftyTwoWeekChangePercent": 7.747495,
    "dividendDate": 1773360000,
    "earningsTimestamp": 1770039000,
    "earningsTimestampStart": 1770039000,
    "earningsTimestampEnd": 1770039000,
    "earningsCallTimestampStart": 1770040800,
    "earningsCallTimestampEnd": 1770040800,
    "isEarningsDateEstimate": false,
    "epsTrailingTwelveMonths": 1.33,
    "epsForward": 4.37683,
    "epsCurrentYear": 3.85938,
    "cryptoTradeable": false,
    "corporateActions": [],
    "regularMarketTime": 1768409197,
    "exchange": "NYQ",
    "messageBoardId": "finmb_190636",
    "exchangeTimezoneName": "America/New_York",
    "exchangeTimezoneShortName": "EST",
    "gmtOffSetMilliseconds": -18000000,
    "market": "us_market",
    "esgPopulated": false,
    "regularMarketChangePercent": 0.46604323,
    "regularMarketPrice": 60.36,
    "shortName": "Tyson Foods, Inc.",
    "longName": "Tyson Foods, Inc.",
    "displayName": "Tyson Foods",
    "trailingPegRatio": 0.3404
  }
}