{
  "ticker": "DXG.VN",
  "crprice": 15700.0,
  "mck_info": {
    "address1": "2W Ung Van Khiem",
    "address2": "Ward 25 Binh Thanh District",
    "city": "Ho Chi Minh City",
    "country": "Vietnam",
    "phone": "84 28 6252 5252",
    "fax": "84 28 6285 3896",
    "website": "https://www.datxanh.vn",
    "industry": "Real Estate - Diversified",
    "industryKey": "real-estate-diversified",
    "industryDisp": "Real Estate - Diversified",
    "sector": "Real Estate",
    "sectorKey": "real-estate",
    "sectorDisp": "Real Estate",
    "longBusinessSummary": "Dat Xanh Group Joint Stock Company engages in the real estate business in Vietnam. The company is involved in the real estate development and investment business; provision of construction services and construction materials; and development of industrial parks, as well as undertakes apartment and commercial apartment projects. The company also provides real estate services, such as consulting, purchasing, brokerage, pricing, real estate management and activation, financial services, etc. In addition, it operates a technology platform, which offers project information that helps the buying and selling process. Dat Xanh Group Joint Stock Company was founded in 2003 and is headquartered in Ho Chi Minh City, Vietnam.",
    "fullTimeEmployees": 3516,
    "companyOfficers": [
      {
        "maxAge": 1,
        "name": "Mr. Bui Ngoc Duc",
        "age": 49,
        "title": "General Director, Member of Executive Board & Director",
        "yearBorn": 1976,
        "exercisedValue": 0,
        "unexercisedValue": 0
      },
      {
        "maxAge": 1,
        "name": "Mr. Son Truong Nguyen",
        "title": "Deputy General Director & Member of Executive Board",
        "exercisedValue": 0,
        "unexercisedValue": 0
      },
      {
        "maxAge": 1,
        "name": "Mr. Van Bac Duong",
        "title": "Deputy General Director & Member of Executive Board",
        "exercisedValue": 0,
        "unexercisedValue": 0
      },
      {
        "maxAge": 1,
        "name": "Mr. Van Hung Le",
        "title": "Deputy General Director & Member of Executive Board",
        "exercisedValue": 0,
        "unexercisedValue": 0
      },
      {
        "maxAge": 1,
        "name": "Mr. Hao  Le",
        "title": "Deputy General Director & Member of Executive Board",
        "exercisedValue": 0,
        "unexercisedValue": 0
      },
      {
        "maxAge": 1,
        "name": "Ms. Thanh Thao Bui",
        "title": "Chief Accountant & Member of Executive Board",
        "exercisedValue": 0,
        "unexercisedValue": 0
      },
      {
        "maxAge": 1,
        "name": "Mr. Hieu Duc Ha",
        "title": "Head of Investment & Financial Board, Secretary and Director",
        "exercisedValue": 0,
        "unexercisedValue": 0
      }
    ],
    "executiveTeam": [],
    "maxAge": 86400,
    "priceHint": 2,
    "previousClose": 15900.0,
    "open": 15950.0,
    "dayLow": 15700.0,
    "dayHigh": 16150.0,
    "regularMarketPreviousClose": 15900.0,
    "regularMarketOpen": 15950.0,
    "regularMarketDayLow": 15700.0,
    "regularMarketDayHigh": 16150.0,
    "exDividendDate": 1494806400,
    "payoutRatio": 0.0,
    "beta": 1.171,
    "trailingPE": 40.13908,
    "forwardPE": 26.309175,
    "volume": 12086557,
    "regularMarketVolume": 12086557,
    "averageVolume": 15841160,
    "averageVolume10days": 16206101,
    "averageDailyVolume10Day": 16206101,
    "bid": 15700.0,
    "ask": 15750.0,
    "bidSize": 0,
    "askSize": 0,
    "marketCap": 15996480913408,
    "fiftyTwoWeekLow": 10512.82,
    "fiftyTwoWeekHigh": 24500.0,
    "allTimeHigh": 40555.555,
    "allTimeLow": 1745.5782,
    "priceToSalesTrailing12Months": 3.703749,
    "fiftyDayAverage": 17917.0,
    "twoHundredDayAverage": 18106.135,
    "trailingAnnualDividendRate": 0.0,
    "trailingAnnualDividendYield": 0.0,
    "currency": "VND",
    "tradeable": false,
    "enterpriseValue": 25076778926080,
    "profitMargins": 0.08881,
    "floatShares": 830696279,
    "sharesOutstanding": 1018884189,
    "heldPercentInsiders": 0.26823,
    "heldPercentInstitutions": 0.16412,
    "impliedSharesOutstanding": 1018884189,
    "bookValue": 12254.842,
    "priceToBook": 1.2811263,
    "lastFiscalYearEnd": 1735603200,
    "nextFiscalYearEnd": 1767139200,
    "mostRecentQuarter": 1759190400,
    "earningsQuarterlyGrowth": 2.023,
    "netIncomeToCommon": 376006508544,
    "trailingEps": 391.14,
    "forwardEps": 596.75,
    "lastSplitFactor": "1.17:1",
    "lastSplitDate": 1748995200,
    "enterpriseToRevenue": 5.806,
    "enterpriseToEbitda": 21.211,
    "52WeekChange": 0.24852347,
    "SandP52WeekChange": 0.14725316,
    "quoteType": "EQUITY",
    "currentPrice": 15700.0,
    "targetHighPrice": 26600.0,
    "targetLowPrice": 18717.95,
    "targetMeanPrice": 23836.324,
    "targetMedianPrice": 24100.0,
    "recommendationKey": "none",
    "numberOfAnalystOpinions": 6,
    "totalCash": 3928288657408,
    "totalCashPerShare": 3855.481,
    "ebitda": 1182265638912,
    "totalDebt": 6338831712256,
    "quickRatio": 0.484,
    "currentRatio": 2.701,
    "totalRevenue": 4318996987904,
    "debtToEquity": 33.446,
    "revenuePerShare": 4759.696,
    "returnOnAssets": 0.02242,
    "returnOnEquity": 0.04164,
    "grossProfits": 2365683138560,
    "freeCashflow": -186030620672,
    "operatingCashflow": 576450265088,
    "earningsGrowth": 1.655,
    "revenueGrowth": 0.055,
    "grossMargins": 0.54774,
    "ebitdaMargins": 0.27374,
    "operatingMargins": 0.21757,
    "financialCurrency": "VND",
    "symbol": "DXG.VN",
    "language": "en-US",
    "region": "US",
    "typeDisp": "Equity",
    "triggerable": false,
    "customPriceAlertConfidence": "LOW",
    "hasPrePostMarketData": false,
    "firstTradeDateMilliseconds": 1261447200000,
    "regularMarketChange": -200.0,
    "regularMarketDayRange": "15700.0 - 16150.0",
    "fullExchangeName": "HOSE",
    "averageDailyVolume3Month": 15841160,
    "fiftyTwoWeekLowChange": 5187.1797,
    "fiftyTwoWeekLowChangePercent": 0.49341467,
    "fiftyTwoWeekRange": "10512.82 - 24500.0",
    "fiftyTwoWeekHighChange": -8800.0,
    "fiftyTwoWeekHighChangePercent": -0.35918367,
    "fiftyTwoWeekChangePercent": 24.852348,
    "earningsTimestampStart": 1753700340,
    "earningsTimestampEnd": 1754049600,
    "isEarningsDateEstimate": true,
    "epsTrailingTwelveMonths": 391.14,
    "epsForward": 596.75,
    "epsCurrentYear": 326.5641,
    "shortName": "DAT XANH GROUP JOINT STOCK CO",
    "longName": "Dat Xanh Group Joint Stock Company",
    "priceEpsCurrentYear": 48.07632,
    "fiftyDayAverageChange": -2217.0,
    "fiftyDayAverageChangePercent": -0.12373723,
    "twoHundredDayAverageChange": -2406.1348,
    "twoHundredDayAverageChangePercent": -0.13289058,
    "sourceInterval": 15,
    "exchangeDataDelayedBy": 15,
    "cryptoTradeable": false,
    "marketState": "POSTPOST",
    "corporateActions": [],
    "regularMarketTime": 1768808707,
    "exchange": "VSE",
    "messageBoardId": "finmb_83274426",
    "exchangeTimezoneName": "Asia/Bangkok",
    "exchangeTimezoneShortName": "ICT",
    "gmtOffSetMilliseconds": 25200000,
    "market": "vn_market",
    "esgPopulated": false,
    "regularMarketChangePercent": -1.2578616,
    "regularMarketPrice": 15700.0,
    "trailingPegRatio": null
  }
}