{
  "https://fiscal.ai/company/NYSE-HSY/": {
    "Rev 3Yr": "4.4%",
    "Rev 5Yr": "7.4%",
    "Rev 10Yr": "4.4%",
    "Dil EPS 3Yr": "-4.4%",
    "Dil EPS 5Yr": "3.3%",
    "Dil EPS 10Yr": "11.4%",
    "Rev Fwd 2Yr": "3.4%",
    "EBITDA Fwd 2Yr": "-7.8%",
    "EPS Fwd 2Yr": "-21.7%",
    "EPS LT Growth Est": "-0.3%"
  },
  "https://finance.yahoo.com/quote/HSY/key-statistics?p=HSY": {
    "__type__": "bs4_tag",
    "html": "<section class=\"yf-18eg72q\" data-testid=\"qsp-statistics\">\n <header class=\"medium mb-4 yf-1kayatz font-condensed\">\n  <h3 class=\"header yf-1kayatz\">\n   Valuation Measures\n  </h3>\n </header>\n <div class=\"table-container yf-18eg72q\">\n  <table class=\"table yf-18eg72q\">\n   <thead>\n    <tr class=\"yf-18eg72q\">\n     <th class=\"yf-18eg72q\">\n     </th>\n     <th class=\"yf-18eg72q\">\n      Current\n     </th>\n     <th class=\"yf-18eg72q\">\n      9/30/2025\n     </th>\n     <th class=\"yf-18eg72q\">\n      6/30/2025\n     </th>\n     <th class=\"yf-18eg72q\">\n      3/31/2025\n     </th>\n     <th class=\"yf-18eg72q\">\n      12/31/2024\n     </th>\n     <th class=\"yf-18eg72q\">\n      9/30/2024\n     </th>\n    </tr>\n   </thead>\n   <tbody>\n    <tr class=\"yf-18eg72q alt\">\n     <td class=\"yf-18eg72q\">\n      Market Cap\n     </td>\n     <td class=\"yf-18eg72q\">\n      39.60B\n     </td>\n     <td class=\"yf-18eg72q\">\n      37.93B\n     </td>\n     <td class=\"yf-18eg72q\">\n      33.63B\n     </td>\n     <td class=\"yf-18eg72q\">\n      34.65B\n     </td>\n     <td class=\"yf-18eg72q\">\n      34.27B\n     </td>\n     <td class=\"yf-18eg72q\">\n      38.81B\n     </td>\n    </tr>\n    <tr class=\"yf-18eg72q\">\n     <td class=\"yf-18eg72q\">\n      Enterprise Value\n     </td>\n     <td class=\"yf-18eg72q\">\n      44.18B\n     </td>\n     <td class=\"yf-18eg72q\">\n      43.02B\n     </td>\n     <td class=\"yf-18eg72q\">\n      38.41B\n     </td>\n     <td class=\"yf-18eg72q\">\n      39.37B\n     </td>\n     <td class=\"yf-18eg72q\">\n      39.30B\n     </td>\n     <td class=\"yf-18eg72q\">\n      44.10B\n     </td>\n    </tr>\n    <tr class=\"yf-18eg72q alt\">\n     <td class=\"yf-18eg72q\">\n      Trailing P/E\n     </td>\n     <td class=\"yf-18eg72q\">\n      29.19\n     </td>\n     <td class=\"yf-18eg72q\">\n      24.83\n     </td>\n     <td class=\"yf-18eg72q\">\n      20.41\n     </td>\n     <td class=\"yf-18eg72q\">\n      15.66\n     </td>\n     <td class=\"yf-18eg72q\">\n      19.47\n     </td>\n     <td class=\"yf-18eg72q\">\n      21.24\n     </td>\n    </tr>\n    <tr class=\"yf-18eg72q\">\n     <td class=\"yf-18eg72q\">\n      Forward P/E\n     </td>\n     <td class=\"yf-18eg72q\">\n      29.15\n     </td>\n     <td class=\"yf-18eg72q\">\n      28.82\n     </td>\n     <td class=\"yf-18eg72q\">\n      28.01\n     </td>\n     <td class=\"yf-18eg72q\">\n      27.78\n     </td>\n     <td class=\"yf-18eg72q\">\n      19.68\n     </td>\n     <td class=\"yf-18eg72q\">\n      20.20\n     </td>\n    </tr>\n    <tr class=\"yf-18eg72q alt\">\n     <td class=\"yf-18eg72q\">\n      PEG Ratio (5yr expected)\n     </td>\n     <td class=\"yf-18eg72q\">\n      48.57\n     </td>\n     <td class=\"yf-18eg72q\">\n      48.07\n     </td>\n     <td class=\"yf-18eg72q\">\n      46.64\n     </td>\n     <td class=\"yf-18eg72q\">\n      46.35\n     </td>\n     <td class=\"yf-18eg72q\">\n      4.57\n     </td>\n     <td class=\"yf-18eg72q\">\n      4.04\n     </td>\n    </tr>\n    <tr class=\"yf-18eg72q\">\n     <td class=\"yf-18eg72q\">\n      Price/Sales\n     </td>\n     <td class=\"yf-18eg72q\">\n      4.38\n     </td>\n     <td class=\"yf-18eg72q\">\n      4.27\n     </td>\n     <td class=\"yf-18eg72q\">\n      3.98\n     </td>\n     <td class=\"yf-18eg72q\">\n      3.94\n     </td>\n     <td class=\"yf-18eg72q\">\n      3.14\n     </td>\n     <td class=\"yf-18eg72q\">\n      4.03\n     </td>\n    </tr>\n    <tr class=\"yf-18eg72q alt\">\n     <td class=\"yf-18eg72q\">\n      Price/Book\n     </td>\n     <td class=\"yf-18eg72q\">\n      8.68\n     </td>\n     <td class=\"yf-18eg72q\">\n      8.40\n     </td>\n     <td class=\"yf-18eg72q\">\n      7.18\n     </td>\n     <td class=\"yf-18eg72q\">\n      9.33\n     </td>\n     <td class=\"yf-18eg72q\">\n      8.15\n     </td>\n     <td class=\"yf-18eg72q\">\n      9.68\n     </td>\n    </tr>\n    <tr class=\"yf-18eg72q\">\n     <td class=\"yf-18eg72q\">\n      Enterprise Value/Revenue\n     </td>\n     <td class=\"yf-18eg72q\">\n      3.85\n     </td>\n     <td class=\"yf-18eg72q\">\n      3.81\n     </td>\n     <td class=\"yf-18eg72q\">\n      3.57\n     </td>\n     <td class=\"yf-18eg72q\">\n      3.51\n     </td>\n     <td class=\"yf-18eg72q\">\n      3.58\n     </td>\n     <td class=\"yf-18eg72q\">\n      4.00\n     </td>\n    </tr>\n    <tr class=\"yf-18eg72q alt\">\n     <td class=\"yf-18eg72q\">\n      Enterprise Value/EBITDA\n     </td>\n     <td class=\"yf-18eg72q\">\n      19.45\n     </td>\n     <td class=\"yf-18eg72q\">\n      17.99\n     </td>\n     <td class=\"yf-18eg72q\">\n      15.60\n     </td>\n     <td class=\"yf-18eg72q\">\n      12.69\n     </td>\n     <td class=\"yf-18eg72q\">\n      14.60\n     </td>\n     <td class=\"yf-18eg72q\">\n      15.69\n     </td>\n    </tr>\n   </tbody>\n  </table>\n </div>\n</section>\n"
  }
}